FRETlines/FRETlines.py
FRETlines/__init__.py
FRETlines/models/__init__.py
FRETlines/models/distance_distributions.py
FRETlines-0.0.5.dist-info/LICENSE
FRETlines-0.0.5.dist-info/METADATA
FRETlines-0.0.5.dist-info/WHEEL
FRETlines-0.0.5.dist-info/top_level.txt
FRETlines-0.0.5.dist-info/RECORD
