Metadata-Version: 2.1
Name: FRETlines
Version: 0.0.5
Summary: Package for the calculation of FRET-lines
Home-page: https://github.com/Fluorescence-Tools/FRETlines
Author: Anders Barth
Author-email: anders.barth@gmail.com
License: UNKNOWN
Platform: UNKNOWN
Classifier: Programming Language :: Python :: 3
Classifier: License :: OSI Approved :: GNU General Public License v3 (GPLv3)
Classifier: Operating System :: OS Independent
License-File: LICENSE
